tune_reporting/__init__.py
tune_reporting/errors/__init__.py
tune_reporting/errors/error_codes.py
tune_reporting/errors/error_desc.py
tune_reporting/errors/errors_traceback.py
tune_reporting/exceptions/__init__.py
tune_reporting/exceptions/base.py
tune_reporting/exceptions/custom.py
tune_reporting/readers/__init__.py
tune_reporting/readers/report_reader_base.py
tune_reporting/readers/report_reader_csv.py
tune_reporting/readers/report_reader_json.py
tune_reporting/support/__init__.py
tune_reporting/support/constants.py
tune_reporting/support/curl.py
tune_reporting/support/utils.py
tune_reporting/tmc/__init__.py
tune_reporting/tmc/tmc_auth_v2_advertiser.py
tune_reporting/tmc/tmc_auth_v2_session_token.py
tune_reporting/tmc/tune_mobileapptracking_api.py
tune_reporting/tmc/tune_mobileapptracking_api_base.py
tune_reporting/tmc/v2/__init__.py
tune_reporting/tmc/v2/management/__init__.py
tune_reporting/tmc/v2/management/tmc_v2_advertiser_sites.py
tune_reporting/tmc/v2/management/tmc_v2_advertisers.py
tune_reporting/tmc/v2/management/tmc_v2_session_authenticate.py
tune_reporting/tmc/v2/reporting/__init__.py
tune_reporting/tmc/v2/reporting/tmc_v2_advertiser_stats_actuals.py
tune_reporting/tmc/v2/reporting/tmc_v2_advertiser_stats_base.py
tune_reporting/tmc/v3/__init__.py
tune_reporting/tmc/v3/reporting/__init__.py
tune_reporting/tmc/v3/reporting/tmc_v3_logs_advertisers_base.py
tune_reporting/tmc/v3/reporting/tmc_v3_logs_advertisers_clicks.py
tune_reporting/tmc/v3/reporting/tmc_v3_logs_advertisers_impressions.py
tune_reporting-2.7.5.dist-info/DESCRIPTION.rst
tune_reporting-2.7.5.dist-info/METADATA
tune_reporting-2.7.5.dist-info/RECORD
tune_reporting-2.7.5.dist-info/WHEEL
tune_reporting-2.7.5.dist-info/metadata.json
tune_reporting-2.7.5.dist-info/top_level.txt
